chesspos/__init__.py
chesspos/evaluation/__init__.py
chesspos/evaluation/monitoring.py
chesspos/models/__init__.py
chesspos/models/autoencoder.py
chesspos/models/cnn_autoencoder.py
chesspos/models/dense.py
chesspos/models/dense_autoencoder.py
chesspos/models/deprecated_models.py
chesspos/models/resnet_autoencoder.py
chesspos/models/saveable_model.py
chesspos/models/trainable_model.py
chesspos/preprocessing/__init__.py
chesspos/preprocessing/board_converter.py
chesspos/preprocessing/game_filters.py
chesspos/preprocessing/game_processors.py
chesspos/preprocessing/pgn_extractor.py
chesspos/preprocessing/sample_generator.py
chesspos/preprocessing/utils.py
chesspos/utils/__init__.py
chesspos/utils/decorators.py
chesspos/utils/utils.py
chesspos-0.1.3.dist-info/LICENSE
chesspos-0.1.3.dist-info/METADATA
chesspos-0.1.3.dist-info/WHEEL
chesspos-0.1.3.dist-info/top_level.txt
chesspos-0.1.3.dist-info/RECORD
