Metadata-Version: 2.1
Name: chesspos
Version: 0.1.3
Summary: A library for manipulating, learning and searching chess positions
Home-page: https://github.com/patrickfrank1/chesspos/
Author: Patrick Frank
Author-email: patrickfrank1@outlook.com
License: GPLv3
Platform: UNKNOWN
Classifier: License :: OSI Approved :: GNU General Public License v3 (GPLv3)
Classifier: Operating System :: OS Independent
Classifier: Programming Language :: Python :: 3
Classifier: Topic :: Scientific/Engineering :: Artificial Intelligence
Classifier: Topic :: Software Development :: Pre-processors
Classifier: Topic :: Games/Entertainment :: Board Games
Requires-Python: >=3.7
License-File: LICENSE
Requires-Dist: chess
Requires-Dist: colorama
Requires-Dist: faiss
Requires-Dist: h5py
Requires-Dist: keras
Requires-Dist: matplotlib
Requires-Dist: numpy
Requires-Dist: scikit-learn
Requires-Dist: setuptools
Requires-Dist: tensorflow
Requires-Dist: pyyaml
